pynodes/__init__.py
pynodes/__main__.py
pynodes/pynodes.py
pynodes/ext/__init__.py
pynodes/ext/santi.py
pynodes-0.0.3.dist-info/DESCRIPTION.rst
pynodes-0.0.3.dist-info/METADATA
pynodes-0.0.3.dist-info/RECORD
pynodes-0.0.3.dist-info/WHEEL
pynodes-0.0.3.dist-info/metadata.json
pynodes-0.0.3.dist-info/top_level.txt
